{
  "project_info": {
    "project_number": "661199678963",
    "project_id": "app-teste-tags",
    "storage_bucket": "app-teste-tags.appspot.com"
  },
  "client": [
    {
      "client_info": {
        "mobilesdk_app_id": "1:661199678963:android:bad240a390e843b8a27686",
        "android_client_info": {
          "package_name": "com.example.tagtrainermobile"
        }
      },
      "oauth_client": [],
      "api_key": [
        {
          "current_key": "AIzaSyCM4jmuHzlnpF7xhBqk3PbXjAdsn-L0DWg"
        }
      ],
      "services": {
        "appinvite_service": {
          "other_platform_oauth_client": []
        }
      }
    }
  ],
  "configuration_version": "1"
}